{
    "generated_at": "2025-01-02T15:24:59+00:00",
    "sport_event": {
        "id": "sr:sport_event:50850323",
        "start_time": "2024-12-26T15:00:00+00:00",
        "start_time_confirmed": true,
        "sport_event_context": {
            "sport": {
                "id": "sr:sport:1",
                "name": "Soccer"
            },
            "category": {
                "id": "sr:category:1",
                "name": "England",
                "country_code": "ENG"
            },
            "competition": {
                "id": "sr:competition:17",
                "name": "Premier League",
                "gender": "men"
            },
            "season": {
                "id": "sr:season:118689",
                "name": "Premier League 24/25",
                "start_date": "2024-08-16",
                "end_date": "2025-05-25",
                "year": "24/25",
                "competition_id": "sr:competition:17"
            },
            "stage": {
                "order": 1,
                "type": "league",
                "phase": "regular season",
                "start_date": "2024-08-16",
                "end_date": "2025-05-25",
                "year": "24/25"
            },
            "round": {
                "number": 18
            },
            "groups": [
                {
                    "id": "sr:league:84075",
                    "name": "Premier League 24/25"
                }
            ]
        },
        "coverage": {
            "type": "sport_event",
            "sport_event_properties": {
                "lineups": true,
                "venue": true,
                "extended_player_stats": true,
                "extended_team_stats": true,
                "lineups_availability": "pre",
                "ballspotting": true,
                "commentary": true,
                "fun_facts": true,
                "goal_scorers": true,
                "scores": "live",
                "game_clock": true,
                "deeper_play_by_play": true,
                "deeper_player_stats": true,
                "deeper_team_stats": true,
                "basic_play_by_play": true,
                "basic_player_stats": true,
                "basic_team_stats": true
            }
        },
        "competitors": [
            {
                "id": "sr:competitor:45",
                "name": "Southampton FC",
                "country": "England",
                "country_code": "ENG",
                "abbreviation": "SOU",
                "qualifier": "home",
                "gender": "male"
            },
            {
                "id": "sr:competitor:37",
                "name": "West Ham United",
                "country": "England",
                "country_code": "ENG",
                "abbreviation": "WHU",
                "qualifier": "away",
                "gender": "male"
            }
        ],
        "venue": {
            "id": "sr:venue:2231",
            "name": "St. Mary's Stadium",
            "capacity": 32505,
            "city_name": "Southampton",
            "country_name": "England",
            "map_coordinates": "50.905833,-1.391111",
            "country_code": "ENG",
            "timezone": "Europe/London"
        },
        "channels": [
            {
                "name": "Canal+ Live 5 HD FR - Astra 1C-1H / 2C (19.2E)",
                "url": "https://www.footao.tv/",
                "country": "France",
                "country_code": "FRA"
            },
            {
                "name": "SKY Sport 252 HD - Hot Bird 1/2/3/4/6 (13.0E)",
                "url": "https://guidatv.sky.it/sport-e-calcio?vista=griglia",
                "country": "Italy",
                "country_code": "ITA"
            },
            {
                "name": "Sky Sport HD 4 (D) - Astra 1C-1H / 2C (19.2E)",
                "url": "https://info.sky.de/inhalt/de/programm_info_live_events_start.jsp",
                "country": "Germany",
                "country_code": "DEU"
            },
            {
                "name": "Bein Sports MAX HD 2 TR - Türksat 1C / Eurasiasat 1 (42.0E)",
                "url": "http://tr.beinsports.com/yayin-akisi/bein-sports-max-2",
                "country": "Turkey",
                "country_code": "TUR"
            },
            {
                "name": "Novasports Start HD - Hot Bird 1/2/3/4/6 (13.0E)",
                "url": "https://www.gazzetta.gr/tv-program",
                "country": "Greece",
                "country_code": "GRC"
            },
            {
                "name": "V Sport Extra HD - Thor 2/3 (1.0W)",
                "url": "https://www.allente.se/tv-guide/",
                "country": "Sweden",
                "country_code": "SWE"
            },
            {
                "name": "Peacock Premium",
                "country": "United States",
                "country_code": "USA"
            }
        ],
        "sport_event_conditions": {
            "referees": [
                {
                    "id": "sr:referee:2094852",
                    "name": "Smith, Lewis",
                    "nationality": "England",
                    "country_code": "ENG",
                    "type": "main_referee"
                },
                {
                    "id": "sr:referee:81871",
                    "name": "Burt, Stuart",
                    "nationality": "England",
                    "country_code": "ENG",
                    "type": "first_assistant_referee"
                },
                {
                    "id": "sr:referee:2053781",
                    "name": "Wood, Timothy",
                    "nationality": "England",
                    "country_code": "ENG",
                    "type": "second_assistant_referee"
                },
                {
                    "id": "sr:referee:81650",
                    "name": "Linington, James",
                    "nationality": "England",
                    "country_code": "ENG",
                    "type": "fourth_official"
                },
                {
                    "id": "sr:referee:52597",
                    "name": "Attwell, Stuart",
                    "nationality": "England",
                    "country_code": "ENG",
                    "type": "video_assistant_referee"
                }
            ],
            "attendance": {
                "count": 31059
            },
            "weather": {
                "pitch_conditions": "good",
                "overall_conditions": "medium"
            },
            "ground": {
                "neutral": false
            },
            "lineups": {
                "confirmed": true
            }
        }
    },
    "sport_event_status": {
        "status": "closed",
        "match_status": "ended",
        "home_score": 0,
        "away_score": 1,
        "winner_id": "sr:competitor:37",
        "period_scores": [
            {
                "home_score": 0,
                "away_score": 0,
                "type": "regular_period",
                "number": 1
            },
            {
                "home_score": 0,
                "away_score": 1,
                "type": "regular_period",
                "number": 2
            }
        ],
        "ball_locations": [
            {
                "order": 4,
                "x": 63,
                "y": 40,
                "qualifier": "away"
            },
            {
                "order": 3,
                "x": 38,
                "y": 59,
                "qualifier": "away"
            },
            {
                "order": 2,
                "x": 32,
                "y": 56,
                "qualifier": "away"
            },
            {
                "order": 1,
                "x": 92,
                "y": 44,
                "qualifier": "away"
            }
        ],
        "match_situation": {
            "status": "safe",
            "qualifier": "away",
            "updated_at": "2024-12-26T17:04:58+00:00"
        }
    },
    "statistics": {
        "totals": {
            "competitors": [
                {
                    "id": "sr:competitor:45",
                    "name": "Southampton FC",
                    "abbreviation": "SOU",
                    "qualifier": "home",
                    "statistics": {
                        "ball_possession": 55,
                        "cards_given": 1,
                        "corner_kicks": 2,
                        "fouls": 13,
                        "free_kicks": 8,
                        "goal_kicks": 9,
                        "injuries": 0,
                        "offsides": 0,
                        "red_cards": 0,
                        "shots_blocked": 3,
                        "shots_off_target": 8,
                        "shots_on_target": 5,
                        "shots_saved": 3,
                        "shots_total": 16,
                        "substitutions": 6,
                        "throw_ins": 19,
                        "yellow_cards": 1,
                        "yellow_red_cards": 0
                    },
                    "players": [
                        {
                            "statistics": {
                                "assists": 0,
                                "corner_kicks": 0,
                                "goals_scored": 0,
                                "offsides": 0,
                                "own_goals": 0,
                                "red_cards": 0,
                                "shots_blocked": 0,
                                "shots_off_target": 0,
                                "shots_on_target": 0,
                                "substituted_in": 1,
                                "substituted_out": 0,
                                "yellow_cards": 0,
                                "yellow_red_cards": 0
                            },
                            "id": "sr:player:17054",
                            "name": "Lallana, Adam",
                            "starter": false
                        },
                        {
                            "statistics": {
                                "assists": 0,
                                "corner_kicks": 0,
                                "goals_scored": 0,
                                "offsides": 0,
                                "own_goals": 0,
                                "red_cards": 0,
                                "shots_blocked": 0,
                                "shots_off_target": 0,
                                "shots_on_target": 0,
                                "substituted_in": 0,
                                "substituted_out": 0,
                                "yellow_cards": 0,
                                "yellow_red_cards": 0
                            },
                            "id": "sr:player:45502",
                            "name": "McCarthy, Alex",
                            "starter": false
                        },
                        {
                            "statistics": {
                                "assists": 0,
                                "corner_kicks": 0,
                                "goals_scored": 0,
                                "offsides": 0,
                                "own_goals": 0,
                                "red_cards": 0,
                                "shots_blocked": 0,
                                "shots_off_target": 0,
                                "shots_on_target": 0,
                                "substituted_in": 0,
                                "substituted_out": 0,
                                "yellow_cards": 0,
                                "yellow_red_cards": 0
                            },
                            "id": "sr:player:138261",
                            "name": "Fraser, Ryan",
                            "starter": false
                        },
                        {
                            "statistics": {
                                "assists": 0,
                                "corner_kicks": 0,
                                "goals_scored": 0,
                                "offsides": 0,
                                "own_goals": 0,
                                "red_cards": 0,
                                "shots_blocked": 0,
                                "shots_off_target": 0,
                                "shots_on_target": 0,
                                "substituted_in": 0,
                                "substituted_out": 0,
                                "yellow_cards": 0,
                                "yellow_red_cards": 0
                            },
                            "id": "sr:player:286085",
                            "name": "Bednarek, Jan",
                            "starter": true
                        },
                        {
                            "statistics": {
                                "assists": 0,
                                "corner_kicks": 0,
                                "goals_scored": 0,
                                "offsides": 0,
                                "own_goals": 0,
                                "red_cards": 0,
                                "shots_blocked": 1,
                                "shots_off_target": 4,
                                "shots_on_target": 2,
                                "substituted_in": 0,
                                "substituted_out": 0,
                                "yellow_cards": 0,
                                "yellow_red_cards": 0
                            },
                            "id": "sr:player:295123",
                            "name": "Onuachu, Paul",
                            "starter": true
                        },
                        {
                            "statistics": {
                                "assists": 0,
                                "corner_kicks": 0,
                                "goals_scored": 0,
                                "offsides": 0,
                                "own_goals": 0,
                                "red_cards": 0,
                                "shots_blocked": 0,
                                "shots_off_target": 0,
                                "shots_on_target": 0,
                                "substituted_in": 1,
                                "substituted_out": 0,
                                "yellow_cards": 0,
                                "yellow_red_cards": 0
                            },
                            "id": "sr:player:328701",
                            "name": "Manning, Ryan",
                            "starter": false
                        },
                        {
                            "statistics": {
                                "assists": 0,
                                "corner_kicks": 0,
                                "goals_scored": 0,
                                "offsides": 0,
                                "own_goals": 0,
                                "red_cards": 0,
                                "shots_blocked": 0,
                                "shots_off_target": 1,
                                "shots_on_target": 0,
                                "substituted_in": 0,
                                "substituted_out": 1,
                                "yellow_cards": 0,
                                "yellow_red_cards": 0
                            },
                            "id": "sr:player:361352",
                            "name": "Armstrong, Adam",
                            "starter": true
                        },
                        {
                            "statistics": {
                                "assists": 0,
                                "corner_kicks": 0,
                                "goals_scored": 0,
                                "offsides": 0,
                                "own_goals": 0,
                                "red_cards": 0,
                                "shots_blocked": 0,
                                "shots_off_target": 0,
                                "shots_on_target": 0,
                                "substituted_in": 1,
                                "substituted_out": 0,
                                "yellow_cards": 0,
                                "yellow_red_cards": 0
                            },
                            "id": "sr:player:555406",
                            "name": "Bree, James",
                            "starter": false
                        },
                        {
                            "statistics": {
                                "assists": 0,
                                "corner_kicks": 0,
                                "goals_scored": 0,
                                "offsides": 0,
                                "own_goals": 0,
                                "red_cards": 0,
                                "shots_blocked": 0,
                                "shots_off_target": 0,
                                "shots_on_target": 2,
                                "substituted_in": 0,
                                "substituted_out": 1,
                                "yellow_cards": 0,
                                "yellow_red_cards": 0
                            },
                            "id": "sr:player:920380",
                            "name": "Walker-Peters, Kyle",
                            "starter": true
                        },
                        {
                            "statistics": {
                                "assists": 0,
                                "corner_kicks": 0,
                                "goals_scored": 0,
                                "offsides": 0,
                                "own_goals": 0,
                                "red_cards": 0,
                                "shots_blocked": 0,
                                "shots_off_target": 0,
                                "shots_on_target": 0,
                                "substituted_in": 0,
                                "substituted_out": 0,
                                "yellow_cards": 0,
                                "yellow_red_cards": 0
                            },
                            "id": "sr:player:988185",
                            "name": "Ramsdale, Aaron",
                            "starter": true
                        },
                        {
                            "statistics": {
                                "assists": 0,
                                "corner_kicks": 0,
                                "goals_scored": 0,
                                "offsides": 0,
                                "own_goals": 0,
                                "red_cards": 0,
                                "shots_blocked": 0,
                                "shots_off_target": 0,
                                "shots_on_target": 0,
                                "substituted_in": 1,
                                "substituted_out": 0,
                                "yellow_cards": 0,
                                "yellow_red_cards": 0
                            },
                            "id": "sr:player:1084012",
                            "name": "Aribo, Joe",
                            "starter": false
                        },
                        {
                            "statistics": {
                                "assists": 0,
                                "corner_kicks": 0,
                                "goals_scored": 0,
                                "offsides": 0,
                                "own_goals": 0,
                                "red_cards": 0,
                                "shots_blocked": 0,
                                "shots_off_target": 1,
                                "shots_on_target": 0,
                                "substituted_in": 0,
                                "substituted_out": 1,
                                "yellow_cards": 0,
                                "yellow_red_cards": 0
                            },
                            "id": "sr:player:1132685",
                            "name": "Downes, Flynn",
                            "starter": true
                        },
                        {
                            "statistics": {
                                "assists": 0,
                                "corner_kicks": 0,
                                "goals_scored": 0,
                                "offsides": 0,
                                "own_goals": 0,
                                "red_cards": 0,
                                "shots_blocked": 1,
                                "shots_off_target": 0,
                                "shots_on_target": 0,
                                "substituted_in": 0,
                                "substituted_out": 1,
                                "yellow_cards": 0,
                                "yellow_red_cards": 0
                            },
                            "id": "sr:player:1322500",
                            "name": "Sugawara, Yukinari",
                            "starter": true
                        },
                        {
                            "statistics": {
                                "assists": 0,
                                "corner_kicks": 0,
                                "goals_scored": 0,
                                "offsides": 0,
                                "own_goals": 0,
                                "red_cards": 0,
                                "shots_blocked": 0,
                                "shots_off_target": 0,
                                "shots_on_target": 0,
                                "substituted_in": 0,
                                "substituted_out": 0,
                                "yellow_cards": 1,
                                "yellow_red_cards": 0
                            },
                            "id": "sr:player:1555691",
                            "name": "Wood, Nathan",
                            "starter": true
                        },
                        {
                            "statistics": {
                                "assists": 0,
                                "corner_kicks": 0,
                                "goals_scored": 0,
                                "offsides": 0,
                                "own_goals": 0,
                                "red_cards": 0,
                                "shots_blocked": 0,
                                "shots_off_target": 0,
                                "shots_on_target": 0,
                                "substituted_in": 0,
                                "substituted_out": 0,
                                "yellow_cards": 0,
                                "yellow_red_cards": 0
                            },
                            "id": "sr:player:1628260",
                            "name": "Harwood-Bellis, Taylor",
                            "starter": true
                        },
                        {
                            "statistics": {
                                "assists": 0,
                                "corner_kicks": 0,
                                "goals_scored": 0,
                                "offsides": 0,
                                "own_goals": 0,
                                "red_cards": 0,
                                "shots_blocked": 0,
                                "shots_off_target": 0,
                                "shots_on_target": 0,
                                "substituted_in": 0,
                                "substituted_out": 0,
                                "yellow_cards": 0,
                                "yellow_red_cards": 0
                            },
                            "id": "sr:player:1868542",
                            "name": "Archer, Cameron",
                            "starter": false
                        },
                        {
                            "statistics": {
                                "assists": 0,
                                "corner_kicks": 0,
                                "goals_scored": 0,
                                "offsides": 0,
                                "own_goals": 0,
                                "red_cards": 0,
                                "shots_blocked": 0,
                                "shots_off_target": 0,
                                "shots_on_target": 0,
                                "substituted_in": 1,
                                "substituted_out": 0,
                                "yellow_cards": 0,
                                "yellow_red_cards": 0
                            },
                            "id": "sr:player:2021829",
                            "name": "Sulemana, Kamaldeen",
                            "starter": false
                        },
                        {
                            "statistics": {
                                "assists": 0,
                                "corner_kicks": 0,
                                "goals_scored": 0,
                                "offsides": 0,
                                "own_goals": 0,
                                "red_cards": 0,
                                "shots_blocked": 1,
                                "shots_off_target": 0,
                                "shots_on_target": 0,
                                "substituted_in": 0,
                                "substituted_out": 1,
                                "yellow_cards": 0,
                                "yellow_red_cards": 0
                            },
                            "id": "sr:player:2059271",
                            "name": "Ugochukwu, Lesley",
                            "starter": true
                        },
                        {
                            "statistics": {
                                "assists": 0,
                                "corner_kicks": 0,
                                "goals_scored": 0,
                                "offsides": 0,
                                "own_goals": 0,
                                "red_cards": 0,
                                "shots_blocked": 0,
                                "shots_off_target": 1,
                                "shots_on_target": 1,
                                "substituted_in": 0,
                                "substituted_out": 1,
                                "yellow_cards": 0,
                                "yellow_red_cards": 0
                            },
                            "id": "sr:player:2221324",
                            "name": "Fernandes, Mateus",
                            "starter": true
                        },
                        {
                            "statistics": {
                                "assists": 0,
                                "corner_kicks": 0,
                                "goals_scored": 0,
                                "offsides": 0,
                                "own_goals": 0,
                                "red_cards": 0,
                                "shots_blocked": 0,
                                "shots_off_target": 1,
                                "shots_on_target": 0,
                                "substituted_in": 1,
                                "substituted_out": 0,
                                "yellow_cards": 0,
                                "yellow_red_cards": 0
                            },
                            "id": "sr:player:2346621",
                            "name": "Dibling, Tyler",
                            "starter": false
                        }
                    ]
                },
                {
                    "id": "sr:competitor:37",
                    "name": "West Ham United",
                    "abbreviation": "WHU",
                    "qualifier": "away",
                    "statistics": {
                        "ball_possession": 45,
                        "cards_given": 2,
                        "corner_kicks": 2,
                        "fouls": 8,
                        "free_kicks": 13,
                        "goal_kicks": 11,
                        "injuries": 2,
                        "offsides": 0,
                        "red_cards": 0,
                        "shots_blocked": 5,
                        "shots_off_target": 7,
                        "shots_on_target": 4,
                        "shots_saved": 5,
                        "shots_total": 16,
                        "substitutions": 6,
                        "throw_ins": 10,
                        "yellow_cards": 2,
                        "yellow_red_cards": 0
                    },
                    "players": [
                        {
                            "statistics": {
                                "assists": 0,
                                "corner_kicks": 0,
                                "goals_scored": 0,
                                "offsides": 0,
                                "own_goals": 0,
                                "red_cards": 0,
                                "shots_blocked": 0,
                                "shots_off_target": 0,
                                "shots_on_target": 0,
                                "substituted_in": 0,
                                "substituted_out": 1,
                                "yellow_cards": 0,
                                "yellow_red_cards": 0
                            },
                            "id": "sr:player:15479",
                            "name": "Fabianski, Lukasz",
                            "starter": true
                        },
                        {
                            "statistics": {
                                "assists": 0,
                                "corner_kicks": 0,
                                "goals_scored": 0,
                                "offsides": 0,
                                "own_goals": 0,
                                "red_cards": 0,
                                "shots_blocked": 0,
                                "shots_off_target": 0,
                                "shots_on_target": 0,
                                "substituted_in": 1,
                                "substituted_out": 0,
                                "yellow_cards": 0,
                                "yellow_red_cards": 0
                            },
                            "id": "sr:player:43443",
                            "name": "Cresswell, Aaron",
                            "starter": false
                        },
                        {
                            "statistics": {
                                "assists": 0,
                                "corner_kicks": 0,
                                "goals_scored": 0,
                                "offsides": 0,
                                "own_goals": 0,
                                "red_cards": 0,
                                "shots_blocked": 0,
                                "shots_off_target": 0,
                                "shots_on_target": 0,
                                "substituted_in": 1,
                                "substituted_out": 0,
                                "yellow_cards": 0,
                                "yellow_red_cards": 0
                            },
                            "id": "sr:player:96531",
                            "name": "Areola, Alphonse",
                            "starter": false
                        },
                        {
                            "statistics": {
                                "assists": 0,
                                "corner_kicks": 0,
                                "goals_scored": 0,
                                "offsides": 0,
                                "own_goals": 0,
                                "red_cards": 0,
                                "shots_blocked": 0,
                                "shots_off_target": 0,
                                "shots_on_target": 0,
                                "substituted_in": 0,
                                "substituted_out": 0,
                                "yellow_cards": 0,
                                "yellow_red_cards": 0
                            },
                            "id": "sr:player:130181",
                            "name": "Ings, Danny",
                            "starter": false
                        },
                        {
                            "statistics": {
                                "assists": 1,
                                "corner_kicks": 0,
                                "goals_scored": 0,
                                "offsides": 0,
                                "own_goals": 0,
                                "red_cards": 0,
                                "shots_blocked": 0,
                                "shots_off_target": 0,
                                "shots_on_target": 0,
                                "substituted_in": 0,
                                "substituted_out": 1,
                                "yellow_cards": 0,
                                "yellow_red_cards": 0
                            },
                            "id": "sr:player:132645",
                            "name": "Fullkrug, Niclas",
                            "starter": true
                        },
                        {
                            "statistics": {
                                "assists": 0,
                                "corner_kicks": 0,
                                "goals_scored": 0,
                                "offsides": 0,
                                "own_goals": 0,
                                "red_cards": 0,
                                "shots_blocked": 0,
                                "shots_off_target": 0,
                                "shots_on_target": 0,
                                "substituted_in": 1,
                                "substituted_out": 0,
                                "yellow_cards": 0,
                                "yellow_red_cards": 0
                            },
                            "id": "sr:player:138024",
                            "name": "Coufal, Vladimir",
                            "starter": false
                        },
                        {
                            "statistics": {
                                "assists": 0,
                                "corner_kicks": 0,
                                "goals_scored": 0,
                                "offsides": 0,
                                "own_goals": 0,
                                "red_cards": 0,
                                "shots_blocked": 1,
                                "shots_off_target": 0,
                                "shots_on_target": 0,
                                "substituted_in": 0,
                                "substituted_out": 1,
                                "yellow_cards": 0,
                                "yellow_red_cards": 0
                            },
                            "id": "sr:player:155997",
                            "name": "Emerson",
                            "starter": true
                        },
                        {
                            "statistics": {
                                "assists": 0,
                                "corner_kicks": 0,
                                "goals_scored": 0,
                                "offsides": 0,
                                "own_goals": 0,
                                "red_cards": 0,
                                "shots_blocked": 0,
                                "shots_off_target": 0,
                                "shots_on_target": 0,
                                "substituted_in": 0,
                                "substituted_out": 0,
                                "yellow_cards": 1,
                                "yellow_red_cards": 0
                            },
                            "id": "sr:player:359840",
                            "name": "Soucek, Tomas",
                            "starter": true
                        },
                        {
                            "statistics": {
                                "assists": 0,
                                "corner_kicks": 0,
                                "goals_scored": 1,
                                "offsides": 0,
                                "own_goals": 0,
                                "red_cards": 0,
                                "shots_blocked": 2,
                                "shots_off_target": 3,
                                "shots_on_target": 1,
                                "substituted_in": 0,
                                "substituted_out": 0,
                                "yellow_cards": 0,
                                "yellow_red_cards": 0
                            },
                            "id": "sr:player:552884",
                            "name": "Bowen, Jarrod",
                            "starter": true
                        },
                        {
                            "statistics": {
                                "assists": 0,
                                "corner_kicks": 0,
                                "goals_scored": 0,
                                "offsides": 0,
                                "own_goals": 0,
                                "red_cards": 0,
                                "shots_blocked": 1,
                                "shots_off_target": 0,
                                "shots_on_target": 0,
                                "substituted_in": 0,
                                "substituted_out": 1,
                                "yellow_cards": 1,
                                "yellow_red_cards": 0
                            },
                            "id": "sr:player:609752",
                            "name": "Rodriguez, Guido",
                            "starter": true
                        },
                        {
                            "statistics": {
                                "assists": 0,
                                "corner_kicks": 1,
                                "goals_scored": 0,
                                "offsides": 0,
                                "own_goals": 0,
                                "red_cards": 0,
                                "shots_blocked": 0,
                                "shots_off_target": 0,
                                "shots_on_target": 1,
                                "substituted_in": 0,
                                "substituted_out": 1,
                                "yellow_cards": 0,
                                "yellow_red_cards": 0
                            },
                            "id": "sr:player:936000",
                            "name": "Soler, Carlos",
                            "starter": true
                        },
                        {
                            "statistics": {
                                "assists": 0,
                                "corner_kicks": 0,
                                "goals_scored": 0,
                                "offsides": 0,
                                "own_goals": 0,
                                "red_cards": 0,
                                "shots_blocked": 0,
                                "shots_off_target": 0,
                                "shots_on_target": 0,
                                "substituted_in": 0,
                                "substituted_out": 0,
                                "yellow_cards": 0,
                                "yellow_red_cards": 0
                            },
                            "id": "sr:player:950080",
                            "name": "Mavropanos, Konstantinos",
                            "starter": true
                        },
                        {
                            "statistics": {
                                "assists": 0,
                                "corner_kicks": 0,
                                "goals_scored": 0,
                                "offsides": 0,
                                "own_goals": 0,
                                "red_cards": 0,
                                "shots_blocked": 0,
                                "shots_off_target": 0,
                                "shots_on_target": 0,
                                "substituted_in": 0,
                                "substituted_out": 0,
                                "yellow_cards": 0,
                                "yellow_red_cards": 0
                            },
                            "id": "sr:player:1012359",
                            "name": "Irving, Andy",
                            "starter": false
                        },
                        {
                            "statistics": {
                                "assists": 0,
                                "corner_kicks": 0,
                                "goals_scored": 0,
                                "offsides": 0,
                                "own_goals": 0,
                                "red_cards": 0,
                                "shots_blocked": 0,
                                "shots_off_target": 0,
                                "shots_on_target": 1,
                                "substituted_in": 1,
                                "substituted_out": 0,
                                "yellow_cards": 0,
                                "yellow_red_cards": 0
                            },
                            "id": "sr:player:1020079",
                            "name": "Alvarez, Edson",
                            "starter": false
                        },
                        {
                            "statistics": {
                                "assists": 0,
                                "corner_kicks": 0,
                                "goals_scored": 0,
                                "offsides": 0,
                                "own_goals": 0,
                                "red_cards": 0,
                                "shots_blocked": 0,
                                "shots_off_target": 2,
                                "shots_on_target": 0,
                                "substituted_in": 0,
                                "substituted_out": 0,
                                "yellow_cards": 0,
                                "yellow_red_cards": 0
                            },
                            "id": "sr:player:1086144",
                            "name": "Wan-Bissaka, Aaron",
                            "starter": true
                        },
                        {
                            "statistics": {
                                "assists": 0,
                                "corner_kicks": 0,
                                "goals_scored": 0,
                                "offsides": 0,
                                "own_goals": 0,
                                "red_cards": 0,
                                "shots_blocked": 0,
                                "shots_off_target": 0,
                                "shots_on_target": 0,
                                "substituted_in": 0,
                                "substituted_out": 1,
                                "yellow_cards": 0,
                                "yellow_red_cards": 0
                            },
                            "id": "sr:player:1263492",
                            "name": "Kilman, Max",
                            "starter": true
                        },
                        {
                            "statistics": {
                                "assists": 0,
                                "corner_kicks": 0,
                                "goals_scored": 0,
                                "offsides": 0,
                                "own_goals": 0,
                                "red_cards": 0,
                                "shots_blocked": 0,
                                "shots_off_target": 1,
                                "shots_on_target": 0,
                                "substituted_in": 1,
                                "substituted_out": 0,
                                "yellow_cards": 0,
                                "yellow_red_cards": 0
                            },
                            "id": "sr:player:1298504",
                            "name": "Summerville, Crysencio",
                            "starter": false
                        },
                        {
                            "statistics": {
                                "assists": 0,
                                "corner_kicks": 0,
                                "goals_scored": 0,
                                "offsides": 0,
                                "own_goals": 0,
                                "red_cards": 0,
                                "shots_blocked": 1,
                                "shots_off_target": 1,
                                "shots_on_target": 1,
                                "substituted_in": 0,
                                "substituted_out": 0,
                                "yellow_cards": 0,
                                "yellow_red_cards": 0
                            },
                            "id": "sr:player:1321798",
                            "name": "Kudus, Mohammed",
                            "starter": true
                        },
                        {
                            "statistics": {
                                "assists": 0,
                                "corner_kicks": 0,
                                "goals_scored": 0,
                                "offsides": 0,
                                "own_goals": 0,
                                "red_cards": 0,
                                "shots_blocked": 0,
                                "shots_off_target": 0,
                                "shots_on_target": 0,
                                "substituted_in": 1,
                                "substituted_out": 0,
                                "yellow_cards": 0,
                                "yellow_red_cards": 0
                            },
                            "id": "sr:player:1561172",
                            "name": "Todibo, Jean-Clair",
                            "starter": false
                        },
                        {
                            "statistics": {
                                "assists": 0,
                                "corner_kicks": 0,
                                "goals_scored": 0,
                                "offsides": 0,
                                "own_goals": 0,
                                "red_cards": 0,
                                "shots_blocked": 0,
                                "shots_off_target": 0,
                                "shots_on_target": 0,
                                "substituted_in": 0,
                                "substituted_out": 0,
                                "yellow_cards": 0,
                                "yellow_red_cards": 0
                            },
                            "id": "sr:player:2582799",
                            "name": "Guilherme, Luis",
                            "starter": false
                        }
                    ]
                }
            ]
        }
    }
}